{
 "actions": [],
 "allow_rename": 1,
 "creation": "2023-03-12 15:20:00.211827",
 "doctype": "DocType",
 "editable_grid": 1,
 "engine": "InnoDB",
 "field_order": [
  "parent_item",
  "item_code",
  "alt_item",
  "item_name",
  "qty",
  "warehouse",
  "uom",
  "rate",
  "currency"
 ],
 "fields": [
  {
   "fieldname": "parent_item",
   "fieldtype": "Link",
   "in_list_view": 1,
   "label": "Parent Item",
   "options": "Item",
   "reqd": 1
  },
  {
   "fieldname": "item_code",
   "fieldtype": "Link",
   "in_list_view": 1,
   "label": "Excluded Item Code",
   "options": "Item",
   "reqd": 1
  },
  {
   "fieldname": "alt_item",
   "fieldtype": "Link",
   "in_list_view": 1,
   "label": "Alternative Item",
   "options": "Item"
  },
  {
   "columns": 1,
   "fieldname": "qty",
   "fieldtype": "Float",
   "in_list_view": 1,
   "label": "Qty",
   "read_only": 1
  },
  {
   "columns": 1,
   "fieldname": "warehouse",
   "fieldtype": "Link",
   "in_list_view": 1,
   "label": "Warehouse",
   "options": "Warehouse"
  },
  {
   "columns": 1,
   "fieldname": "uom",
   "fieldtype": "Link",
   "label": "UOM",
   "options": "UOM"
  },
  {
   "columns": 1,
   "fieldname": "rate",
   "fieldtype": "Data",
   "label": "Rate"
  },
  {
   "columns": 1,
   "fieldname": "currency",
   "fieldtype": "Link",
   "label": "Currency",
   "options": "Currency"
  },
  {
   "fetch_from": "alt_item.name",
   "fieldname": "item_name",
   "fieldtype": "Data",
   "label": "Item Name"
  }
 ],
 "index_web_pages_for_search": 1,
 "istable": 1,
 "links": [],
 "modified": "2023-03-22 09:40:22.132283",
 "modified_by": "Administrator",
 "module": "Sabaintegration",
 "name": "Bundle Delivery Note Excluded Item",
 "owner": "Administrator",
 "permissions": [],
 "sort_field": "modified",
 "sort_order": "DESC"
}